{
  "scraped_at": "2026-03-02T06:38:11.379306+00:00",
  "source": "robotaxitracker.com",
  "description": "Active fleet growth time series",
  "data_points": 101,
  "data": [
    {
      "date": "2025-06-28",
      "total": 11
    },
    {
      "date": "2025-06-30",
      "total": 11
    },
    {
      "date": "2025-07-03",
      "total": 11
    },
    {
      "date": "2025-07-05",
      "total": 11
    },
    {
      "date": "2025-07-08",
      "total": 11
    },
    {
      "date": "2025-07-10",
      "total": 11
    },
    {
      "date": "2025-07-13",
      "total": 11
    },
    {
      "date": "2025-07-15",
      "total": 11
    },
    {
      "date": "2025-07-17",
      "total": 11
    },
    {
      "date": "2025-07-20",
      "total": 11
    },
    {
      "date": "2025-07-22",
      "total": 11
    },
    {
      "date": "2025-07-25",
      "total": 11
    },
    {
      "date": "2025-07-27",
      "total": 11
    },
    {
      "date": "2025-07-30",
      "total": 14
    },
    {
      "date": "2025-08-01",
      "total": 14
    },
    {
      "date": "2025-08-04",
      "total": 14
    },
    {
      "date": "2025-08-06",
      "total": 14
    },
    {
      "date": "2025-08-09",
      "total": 14
    },
    {
      "date": "2025-08-11",
      "total": 14
    },
    {
      "date": "2025-08-14",
      "total": 14
    },
    {
      "date": "2025-08-16",
      "total": 13
    },
    {
      "date": "2025-08-18",
      "total": 13
    },
    {
      "date": "2025-08-21",
      "total": 13
    },
    {
      "date": "2025-08-23",
      "bayarea": 1,
      "total": 14,
      "austin": 13
    },
    {
      "date": "2025-08-26",
      "bayarea": 1,
      "total": 14,
      "austin": 13
    },
    {
      "date": "2025-08-28",
      "bayarea": 1,
      "total": 14,
      "austin": 13
    },
    {
      "date": "2025-08-31",
      "bayarea": 1,
      "total": 14,
      "austin": 13
    },
    {
      "date": "2025-09-02",
      "bayarea": 3,
      "total": 16,
      "austin": 13
    },
    {
      "date": "2025-09-05",
      "bayarea": 11,
      "total": 27,
      "austin": 16
    },
    {
      "date": "2025-09-07",
      "bayarea": 19,
      "total": 39,
      "austin": 20
    },
    {
      "date": "2025-09-10",
      "bayarea": 24,
      "total": 44,
      "austin": 20
    },
    {
      "date": "2025-09-12",
      "bayarea": 28,
      "total": 48,
      "austin": 20
    },
    {
      "date": "2025-09-14",
      "bayarea": 31,
      "total": 51,
      "austin": 20
    },
    {
      "date": "2025-09-17",
      "bayarea": 39,
      "total": 59,
      "austin": 20
    },
    {
      "date": "2025-09-19",
      "bayarea": 50,
      "total": 70,
      "austin": 20
    },
    {
      "date": "2025-09-22",
      "bayarea": 56,
      "total": 77,
      "austin": 21
    },
    {
      "date": "2025-09-24",
      "bayarea": 57,
      "total": 78,
      "austin": 21
    },
    {
      "date": "2025-09-27",
      "bayarea": 59,
      "total": 80,
      "austin": 21
    },
    {
      "date": "2025-09-29",
      "bayarea": 59,
      "total": 80,
      "austin": 21
    },
    {
      "date": "2025-10-02",
      "bayarea": 62,
      "total": 84,
      "austin": 22
    },
    {
      "date": "2025-10-04",
      "bayarea": 64,
      "total": 86,
      "austin": 22
    },
    {
      "date": "2025-10-07",
      "bayarea": 67,
      "total": 89,
      "austin": 22
    },
    {
      "date": "2025-10-09",
      "bayarea": 70,
      "total": 92,
      "austin": 22
    },
    {
      "date": "2025-10-12",
      "bayarea": 80,
      "total": 102,
      "austin": 22
    },
    {
      "date": "2025-10-14",
      "bayarea": 83,
      "total": 105,
      "austin": 22
    },
    {
      "date": "2025-10-16",
      "bayarea": 84,
      "total": 106,
      "austin": 22
    },
    {
      "date": "2025-10-19",
      "bayarea": 84,
      "total": 106,
      "austin": 22
    },
    {
      "date": "2025-10-21",
      "bayarea": 83,
      "total": 105,
      "austin": 22
    },
    {
      "date": "2025-10-24",
      "bayarea": 89,
      "total": 111,
      "austin": 22
    },
    {
      "date": "2025-10-26",
      "bayarea": 91,
      "total": 113,
      "austin": 22
    },
    {
      "date": "2025-10-29",
      "bayarea": 95,
      "total": 117,
      "austin": 22
    },
    {
      "date": "2025-10-31",
      "bayarea": 94,
      "total": 116,
      "austin": 22
    },
    {
      "date": "2025-11-03",
      "bayarea": 97,
      "total": 119,
      "austin": 22
    },
    {
      "date": "2025-11-05",
      "bayarea": 96,
      "total": 119,
      "austin": 23
    },
    {
      "date": "2025-11-08",
      "bayarea": 97,
      "total": 123,
      "austin": 26
    },
    {
      "date": "2025-11-10",
      "bayarea": 101,
      "total": 130,
      "austin": 29
    },
    {
      "date": "2025-11-13",
      "bayarea": 101,
      "total": 130,
      "austin": 29
    },
    {
      "date": "2025-11-15",
      "bayarea": 105,
      "total": 133,
      "austin": 28
    },
    {
      "date": "2025-11-17",
      "bayarea": 106,
      "total": 134,
      "austin": 28
    },
    {
      "date": "2025-11-20",
      "bayarea": 105,
      "total": 133,
      "austin": 28
    },
    {
      "date": "2025-11-22",
      "bayarea": 105,
      "total": 133,
      "austin": 28
    },
    {
      "date": "2025-11-25",
      "bayarea": 131,
      "total": 159,
      "austin": 28
    },
    {
      "date": "2025-11-27",
      "bayarea": 131,
      "total": 159,
      "austin": 28
    },
    {
      "date": "2025-11-30",
      "bayarea": 132,
      "total": 160,
      "austin": 28
    },
    {
      "date": "2025-12-02",
      "bayarea": 102,
      "total": 129,
      "austin": 27
    },
    {
      "date": "2025-12-05",
      "bayarea": 74,
      "total": 101,
      "austin": 27
    },
    {
      "date": "2025-12-07",
      "bayarea": 68,
      "total": 95,
      "austin": 27
    },
    {
      "date": "2025-12-10",
      "bayarea": 58,
      "total": 85,
      "austin": 27
    },
    {
      "date": "2025-12-12",
      "bayarea": 50,
      "total": 77,
      "austin": 27
    },
    {
      "date": "2025-12-15",
      "bayarea": 50,
      "total": 77,
      "austin": 27
    },
    {
      "date": "2025-12-17",
      "bayarea": 46,
      "total": 72,
      "austin": 26
    },
    {
      "date": "2025-12-19",
      "bayarea": 42,
      "total": 68,
      "austin": 26
    },
    {
      "date": "2025-12-22",
      "bayarea": 39,
      "total": 66,
      "austin": 27
    },
    {
      "date": "2025-12-24",
      "bayarea": 37,
      "total": 65,
      "austin": 28
    },
    {
      "date": "2025-12-27",
      "bayarea": 38,
      "total": 63,
      "austin": 25
    },
    {
      "date": "2025-12-29",
      "bayarea": 35,
      "total": 62,
      "austin": 27
    },
    {
      "date": "2026-01-01",
      "bayarea": 37,
      "total": 65,
      "austin": 28
    },
    {
      "date": "2026-01-03",
      "bayarea": 42,
      "total": 69,
      "austin": 27
    },
    {
      "date": "2026-01-06",
      "bayarea": 50,
      "total": 79,
      "austin": 29
    },
    {
      "date": "2026-01-08",
      "bayarea": 55,
      "total": 83,
      "austin": 28
    },
    {
      "date": "2026-01-11",
      "bayarea": 65,
      "total": 91,
      "austin": 26
    },
    {
      "date": "2026-01-13",
      "bayarea": 67,
      "total": 96,
      "austin": 29
    },
    {
      "date": "2026-01-15",
      "bayarea": 64,
      "total": 97,
      "austin": 33
    },
    {
      "date": "2026-01-18",
      "bayarea": 63,
      "total": 94,
      "austin": 31
    },
    {
      "date": "2026-01-20",
      "bayarea": 56,
      "total": 82,
      "austin": 26
    },
    {
      "date": "2026-01-23",
      "bayarea": 57,
      "total": 97,
      "austin": 40
    },
    {
      "date": "2026-01-25",
      "bayarea": 59,
      "total": 99,
      "austin": 40
    },
    {
      "date": "2026-01-28",
      "bayarea": 58,
      "total": 97,
      "austin": 39
    },
    {
      "date": "2026-01-30",
      "bayarea": 55,
      "total": 96,
      "austin": 41
    },
    {
      "date": "2026-02-02",
      "bayarea": 57,
      "total": 99,
      "austin": 42
    },
    {
      "date": "2026-02-04",
      "bayarea": 57,
      "total": 99,
      "austin": 42
    },
    {
      "date": "2026-02-07",
      "bayarea": 57,
      "total": 99,
      "austin": 42
    },
    {
      "date": "2026-02-09",
      "bayarea": 63,
      "total": 107,
      "austin": 44
    },
    {
      "date": "2026-02-12",
      "bayarea": 64,
      "total": 108,
      "austin": 44
    },
    {
      "date": "2026-02-14",
      "bayarea": 76,
      "total": 119,
      "austin": 43
    },
    {
      "date": "2026-02-16",
      "bayarea": 68,
      "total": 105,
      "austin": 37
    },
    {
      "date": "2026-02-19",
      "bayarea": 71,
      "total": 104,
      "austin": 33
    },
    {
      "date": "2026-02-21",
      "bayarea": 51,
      "total": 84,
      "austin": 33
    },
    {
      "date": "2026-02-24",
      "bayarea": 37,
      "total": 70,
      "austin": 33
    },
    {
      "date": "2026-02-26",
      "bayarea": 38,
      "total": 70,
      "austin": 32
    },
    {
      "date": "2026-03-01",
      "bayarea": 43,
      "total": 71,
      "austin": 28
    }
  ]
}