{
  "scraped_at": "2026-02-26T06:39:30.640252+00:00",
  "source": "robotaxitracker.com",
  "description": "Active fleet growth time series",
  "data_points": 101,
  "data": [
    {
      "date": "2025-06-28",
      "total": 11
    },
    {
      "date": "2025-06-30",
      "total": 11
    },
    {
      "date": "2025-07-03",
      "total": 11
    },
    {
      "date": "2025-07-05",
      "total": 11
    },
    {
      "date": "2025-07-07",
      "total": 11
    },
    {
      "date": "2025-07-10",
      "total": 11
    },
    {
      "date": "2025-07-12",
      "total": 11
    },
    {
      "date": "2025-07-15",
      "total": 11
    },
    {
      "date": "2025-07-17",
      "total": 11
    },
    {
      "date": "2025-07-19",
      "total": 11
    },
    {
      "date": "2025-07-22",
      "total": 11
    },
    {
      "date": "2025-07-24",
      "total": 11
    },
    {
      "date": "2025-07-27",
      "total": 11
    },
    {
      "date": "2025-07-29",
      "total": 11
    },
    {
      "date": "2025-08-01",
      "total": 14
    },
    {
      "date": "2025-08-03",
      "total": 14
    },
    {
      "date": "2025-08-05",
      "total": 14
    },
    {
      "date": "2025-08-08",
      "total": 14
    },
    {
      "date": "2025-08-10",
      "total": 14
    },
    {
      "date": "2025-08-13",
      "total": 14
    },
    {
      "date": "2025-08-15",
      "total": 13
    },
    {
      "date": "2025-08-18",
      "total": 13
    },
    {
      "date": "2025-08-20",
      "total": 13
    },
    {
      "date": "2025-08-22",
      "bayarea": 1,
      "total": 14,
      "austin": 13
    },
    {
      "date": "2025-08-25",
      "bayarea": 1,
      "total": 14,
      "austin": 13
    },
    {
      "date": "2025-08-27",
      "bayarea": 1,
      "total": 14,
      "austin": 13
    },
    {
      "date": "2025-08-30",
      "bayarea": 1,
      "total": 14,
      "austin": 13
    },
    {
      "date": "2025-09-01",
      "bayarea": 3,
      "total": 16,
      "austin": 13
    },
    {
      "date": "2025-09-04",
      "bayarea": 7,
      "total": 22,
      "austin": 15
    },
    {
      "date": "2025-09-06",
      "bayarea": 13,
      "total": 30,
      "austin": 17
    },
    {
      "date": "2025-09-08",
      "bayarea": 17,
      "total": 37,
      "austin": 20
    },
    {
      "date": "2025-09-11",
      "bayarea": 23,
      "total": 43,
      "austin": 20
    },
    {
      "date": "2025-09-13",
      "bayarea": 25,
      "total": 45,
      "austin": 20
    },
    {
      "date": "2025-09-15",
      "bayarea": 29,
      "total": 49,
      "austin": 20
    },
    {
      "date": "2025-09-18",
      "bayarea": 36,
      "total": 56,
      "austin": 20
    },
    {
      "date": "2025-09-20",
      "bayarea": 46,
      "total": 66,
      "austin": 20
    },
    {
      "date": "2025-09-23",
      "bayarea": 47,
      "total": 68,
      "austin": 21
    },
    {
      "date": "2025-09-25",
      "bayarea": 48,
      "total": 69,
      "austin": 21
    },
    {
      "date": "2025-09-28",
      "bayarea": 50,
      "total": 71,
      "austin": 21
    },
    {
      "date": "2025-09-30",
      "bayarea": 50,
      "total": 71,
      "austin": 21
    },
    {
      "date": "2025-10-02",
      "bayarea": 53,
      "total": 75,
      "austin": 22
    },
    {
      "date": "2025-10-05",
      "bayarea": 56,
      "total": 78,
      "austin": 22
    },
    {
      "date": "2025-10-07",
      "bayarea": 59,
      "total": 81,
      "austin": 22
    },
    {
      "date": "2025-10-10",
      "bayarea": 63,
      "total": 85,
      "austin": 22
    },
    {
      "date": "2025-10-12",
      "bayarea": 72,
      "total": 94,
      "austin": 22
    },
    {
      "date": "2025-10-15",
      "bayarea": 77,
      "total": 99,
      "austin": 22
    },
    {
      "date": "2025-10-17",
      "bayarea": 78,
      "total": 100,
      "austin": 22
    },
    {
      "date": "2025-10-19",
      "bayarea": 77,
      "total": 99,
      "austin": 22
    },
    {
      "date": "2025-10-22",
      "bayarea": 80,
      "total": 102,
      "austin": 22
    },
    {
      "date": "2025-10-24",
      "bayarea": 83,
      "total": 105,
      "austin": 22
    },
    {
      "date": "2025-10-27",
      "bayarea": 88,
      "total": 110,
      "austin": 22
    },
    {
      "date": "2025-10-29",
      "bayarea": 89,
      "total": 111,
      "austin": 22
    },
    {
      "date": "2025-11-01",
      "bayarea": 88,
      "total": 110,
      "austin": 22
    },
    {
      "date": "2025-11-03",
      "bayarea": 87,
      "total": 109,
      "austin": 22
    },
    {
      "date": "2025-11-05",
      "bayarea": 86,
      "total": 109,
      "austin": 23
    },
    {
      "date": "2025-11-08",
      "bayarea": 86,
      "total": 112,
      "austin": 26
    },
    {
      "date": "2025-11-10",
      "bayarea": 90,
      "total": 119,
      "austin": 29
    },
    {
      "date": "2025-11-13",
      "bayarea": 90,
      "total": 119,
      "austin": 29
    },
    {
      "date": "2025-11-15",
      "bayarea": 94,
      "total": 122,
      "austin": 28
    },
    {
      "date": "2025-11-17",
      "bayarea": 95,
      "total": 123,
      "austin": 28
    },
    {
      "date": "2025-11-20",
      "bayarea": 94,
      "total": 122,
      "austin": 28
    },
    {
      "date": "2025-11-22",
      "bayarea": 94,
      "total": 122,
      "austin": 28
    },
    {
      "date": "2025-11-25",
      "bayarea": 128,
      "total": 156,
      "austin": 28
    },
    {
      "date": "2025-11-27",
      "bayarea": 128,
      "total": 156,
      "austin": 28
    },
    {
      "date": "2025-11-30",
      "bayarea": 129,
      "total": 157,
      "austin": 28
    },
    {
      "date": "2025-12-02",
      "bayarea": 98,
      "total": 125,
      "austin": 27
    },
    {
      "date": "2025-12-04",
      "bayarea": 71,
      "total": 98,
      "austin": 27
    },
    {
      "date": "2025-12-07",
      "bayarea": 64,
      "total": 91,
      "austin": 27
    },
    {
      "date": "2025-12-09",
      "bayarea": 57,
      "total": 84,
      "austin": 27
    },
    {
      "date": "2025-12-12",
      "bayarea": 45,
      "total": 72,
      "austin": 27
    },
    {
      "date": "2025-12-14",
      "bayarea": 47,
      "total": 74,
      "austin": 27
    },
    {
      "date": "2025-12-17",
      "bayarea": 41,
      "total": 67,
      "austin": 26
    },
    {
      "date": "2025-12-19",
      "bayarea": 37,
      "total": 63,
      "austin": 26
    },
    {
      "date": "2025-12-21",
      "bayarea": 34,
      "total": 60,
      "austin": 26
    },
    {
      "date": "2025-12-24",
      "bayarea": 32,
      "total": 60,
      "austin": 28
    },
    {
      "date": "2025-12-26",
      "bayarea": 32,
      "total": 59,
      "austin": 27
    },
    {
      "date": "2025-12-29",
      "bayarea": 29,
      "total": 56,
      "austin": 27
    },
    {
      "date": "2025-12-31",
      "bayarea": 30,
      "total": 58,
      "austin": 28
    },
    {
      "date": "2026-01-03",
      "bayarea": 37,
      "total": 64,
      "austin": 27
    },
    {
      "date": "2026-01-05",
      "bayarea": 46,
      "total": 75,
      "austin": 29
    },
    {
      "date": "2026-01-07",
      "bayarea": 49,
      "total": 78,
      "austin": 29
    },
    {
      "date": "2026-01-10",
      "bayarea": 55,
      "total": 81,
      "austin": 26
    },
    {
      "date": "2026-01-12",
      "bayarea": 64,
      "total": 92,
      "austin": 28
    },
    {
      "date": "2026-01-15",
      "bayarea": 60,
      "total": 93,
      "austin": 33
    },
    {
      "date": "2026-01-17",
      "bayarea": 67,
      "total": 98,
      "austin": 31
    },
    {
      "date": "2026-01-19",
      "bayarea": 53,
      "total": 83,
      "austin": 30
    },
    {
      "date": "2026-01-22",
      "bayarea": 55,
      "total": 87,
      "austin": 32
    },
    {
      "date": "2026-01-24",
      "bayarea": 56,
      "total": 96,
      "austin": 40
    },
    {
      "date": "2026-01-27",
      "bayarea": 52,
      "total": 91,
      "austin": 39
    },
    {
      "date": "2026-01-29",
      "bayarea": 53,
      "total": 94,
      "austin": 41
    },
    {
      "date": "2026-02-01",
      "bayarea": 54,
      "total": 96,
      "austin": 42
    },
    {
      "date": "2026-02-03",
      "bayarea": 52,
      "total": 94,
      "austin": 42
    },
    {
      "date": "2026-02-05",
      "bayarea": 53,
      "total": 95,
      "austin": 42
    },
    {
      "date": "2026-02-08",
      "bayarea": 59,
      "total": 102,
      "austin": 43
    },
    {
      "date": "2026-02-10",
      "bayarea": 58,
      "total": 102,
      "austin": 44
    },
    {
      "date": "2026-02-13",
      "bayarea": 61,
      "total": 104,
      "austin": 43
    },
    {
      "date": "2026-02-15",
      "bayarea": 64,
      "total": 106,
      "austin": 42
    },
    {
      "date": "2026-02-18",
      "bayarea": 60,
      "total": 92,
      "austin": 32
    },
    {
      "date": "2026-02-20",
      "bayarea": 61,
      "total": 93,
      "austin": 32
    },
    {
      "date": "2026-02-22",
      "bayarea": 34,
      "total": 65,
      "austin": 31
    },
    {
      "date": "2026-02-25",
      "bayarea": 32,
      "total": 62,
      "austin": 30
    }
  ]
}